conda_export_history_versions/__init__.py
conda_export_history_versions/parse_conda_env.py
conda_export_history_versions-0.1.8.dist-info/LICENSE
conda_export_history_versions-0.1.8.dist-info/METADATA
conda_export_history_versions-0.1.8.dist-info/WHEEL
conda_export_history_versions-0.1.8.dist-info/entry_points.txt
conda_export_history_versions-0.1.8.dist-info/top_level.txt
conda_export_history_versions-0.1.8.dist-info/RECORD
