Metadata-Version: 2.1
Name: conda-export-history-versions
Version: 0.1.8
Summary: A script for exporting conda environments, combining historical package information with version specifications.
Author-email: David Sestu <david.sestu@gmail.com>
License: MIT License
Project-URL: Homepage, https://github.com/DSestu/conda-export-history-versions
Requires-Python: >=3.6
License-File: LICENSE
Requires-Dist: PyYAML
